graphreader/Text_encoder.py
graphreader/__init__.py
graphreader/document.py
graphreader/graph_class.py
graphreader/graph_reader.py
graphreader/openai_client.py
graphreader/pinecone_client.py
graphreader/tools_utils.py
graphreader-0.0.1.dist-info/METADATA
graphreader-0.0.1.dist-info/WHEEL
graphreader-0.0.1.dist-info/top_level.txt
graphreader-0.0.1.dist-info/RECORD
