Metadata-Version: 2.1
Name: graphreader
Version: 0.0.1
Summary: Implementation of the GraphReader Paper
Author: Atharva Bagde, Sushant Menon
Author-email: sushantmenon1@gmail.com
Classifier: Development Status :: 1 - Planning
Classifier: Intended Audience :: Developers
Classifier: Programming Language :: Python :: 3
Classifier: Operating System :: Unix
Classifier: Operating System :: MacOS :: MacOS X
Classifier: Operating System :: Microsoft :: Windows
Requires-Dist: langchain ==0.3.4
Requires-Dist: langchain-openai ==0.2.3
Requires-Dist: networkx ==3.4.1
Requires-Dist: nltk ==3.9.1
Requires-Dist: openai ==1.52.0
Requires-Dist: pinecone-client ==5.0.1
Requires-Dist: pypdf ==5.0.1
Requires-Dist: sentence-transformers ==3.2.0
Requires-Dist: tqdm ==4.66.5
